[
  {
    "date": "2026-06-10",
    "slots": {
      "Быстрый|10 мин": {
        "count": 146,
        "prices": {
          "420": 16,
          "550": 17,
          "590": 8,
          "640": 66,
          "750": 39
        },
        "avg": 632
      },
      "Детский|5 мин": {
        "count": 358,
        "prices": {
          "150": 35,
          "220": 62,
          "250": 160,
          "300": 69,
          "350": 32
        },
        "avg": 254
      },
      "Быстрый|5 мин": {
        "count": 289,
        "prices": {
          "220": 29,
          "290": 40,
          "300": 23,
          "340": 119,
          "400": 67,
          "490": 11
        },
        "avg": 337
      },
      "Детский|10 мин": {
        "count": 159,
        "prices": {
          "250": 22,
          "420": 10,
          "450": 86,
          "550": 38,
          "650": 3
        },
        "avg": 448
      }
    }
  }
]